MinePI/__init__.py
MinePI/functions.py
MinePI/skin_render.py
MinePI-0.1.dist-info/LICENSE.txt
MinePI-0.1.dist-info/METADATA
MinePI-0.1.dist-info/WHEEL
MinePI-0.1.dist-info/top_level.txt
MinePI-0.1.dist-info/RECORD
