Metadata-Version: 2.1
Name: MinePI
Version: 0.1
Summary: Minecraft utility library.
Home-page: https://github.com/benno1237/MinePI
Author: benno1237, honigkuchen
Author-email: benno.kollreider@gmail.com
License: MIT
Download-URL: https://github.com/benno1237/MinePI/archive/refs/tags/0.1.tar.gz
Keywords: Minecraft,Skin,Render,Head,UUID
Platform: UNKNOWN
Classifier: Development Status :: 3 - Alpha
Classifier: Intended Audience :: Developers
Classifier: Topic :: Software Development :: Build Tools
Classifier: License :: OSI Approved :: MIT License
Classifier: Programming Language :: Python :: 3
Classifier: Programming Language :: Python :: 3.7
Classifier: Programming Language :: Python :: 3.8
Classifier: Programming Language :: Python :: 3.9
License-File: LICENSE.txt
Requires-Dist: aiohttp
Requires-Dist: Pillow
